scrapbook/__init__.py
scrapbook/api.py
scrapbook/encoders.py
scrapbook/exceptions.py
scrapbook/log.py
scrapbook/models.py
scrapbook/schemas.py
scrapbook/scraps.py
scrapbook/utils.py
scrapbook/version.py
scrapbook/schemas/scrap.v1.json
scrapbook/tests/__init__.py
scrapbook/tests/test_api.py
scrapbook/tests/test_encoders.py
scrapbook/tests/test_notebooks.py
scrapbook/tests/test_scrapbooks.py
scrapbook/tests/test_scraps.py
scrapbook/tests/test_utils.py
scrapbook/tests/fixtures/tiny.png
scrapbook/tests/notebooks/record.ipynb
scrapbook/tests/notebooks/result_no_exec.ipynb
scrapbook/tests/notebooks/.ipynb_checkpoints/record-checkpoint.ipynb
scrapbook/tests/notebooks/.ipynb_checkpoints/result reader-checkpoint.ipynb
scrapbook/tests/notebooks/.ipynb_checkpoints/result_no_exec-checkpoint.ipynb
scrapbook/tests/notebooks/collection/result1.ipynb
scrapbook/tests/notebooks/collection/result2.ipynb
scrapbook/tests/notebooks/collection/.ipynb_checkpoints/scrapbook_experimental-checkpoint.ipynb
scrapbook/tests/notebooks/collection/.ipynb_checkpoints/scrapbook_master-checkpoint.ipynb
nteract_scrapbook-0.4.1.dist-info/LICENSE
nteract_scrapbook-0.4.1.dist-info/METADATA
nteract_scrapbook-0.4.1.dist-info/WHEEL
nteract_scrapbook-0.4.1.dist-info/top_level.txt
nteract_scrapbook-0.4.1.dist-info/RECORD
