Metadata-Version: 2.1
Name: nteract-scrapbook
Version: 0.4.1
Summary: A library for recording and reading data in Jupyter and nteract Notebooks
Home-page: https://github.com/nteract/scrapbook
Author: nteract contributors
Author-email: nteract@googlegroups.com
License: BSD
Project-URL: Documentation, https://nteract-scrapbook.readthedocs.io
Project-URL: Funding, https://nteract.io
Project-URL: Source, https://github.com/nteract/scrapbook/
Project-URL: Tracker, https://github.com/nteract/scrapbook/issues
Keywords: jupyter,mapreduce,nteract,pipeline,notebook
Platform: UNKNOWN
Classifier: Intended Audience :: Developers
Classifier: Intended Audience :: System Administrators
Classifier: Intended Audience :: Science/Research
Classifier: License :: OSI Approved :: BSD License
Classifier: Programming Language :: Python
Classifier: Programming Language :: Python :: 3
Classifier: Programming Language :: Python :: 3.5
Classifier: Programming Language :: Python :: 3.6
Classifier: Programming Language :: Python :: 3.7
Classifier: Programming Language :: Python :: 3.8
Requires-Python: >=3.5
Requires-Dist: pandas
Requires-Dist: papermill
Requires-Dist: jsonschema
Requires-Dist: ipython
Requires-Dist: pyarrow
Provides-Extra: all
Requires-Dist: papermill[all] ; extra == 'all'
Provides-Extra: azure
Requires-Dist: papermill[azure] ; extra == 'azure'
Provides-Extra: dev
Requires-Dist: bumpversion ; extra == 'dev'
Requires-Dist: wheel (>=0.31.0) ; extra == 'dev'
Requires-Dist: setuptools (>=38.6.0) ; extra == 'dev'
Requires-Dist: twine (>=1.11.0) ; extra == 'dev'
Requires-Dist: flake8 ; extra == 'dev'
Requires-Dist: tox ; extra == 'dev'
Requires-Dist: mock ; extra == 'dev'
Requires-Dist: ipython ; extra == 'dev'
Requires-Dist: papermill[dev] ; extra == 'dev'
Requires-Dist: pytest (>=4.1) ; extra == 'dev'
Requires-Dist: pytest-cov (>=2.6.1) ; extra == 'dev'
Requires-Dist: pytest-mock (>=1.10) ; extra == 'dev'
Requires-Dist: pytest-env (>=0.6.2) ; extra == 'dev'
Requires-Dist: codecov ; extra == 'dev'
Requires-Dist: coverage ; extra == 'dev'
Provides-Extra: gcs
Requires-Dist: papermill[gcs] ; extra == 'gcs'
Provides-Extra: s3
Requires-Dist: papermill[s3] ; extra == 's3'
Provides-Extra: test
Requires-Dist: bumpversion ; extra == 'test'
Requires-Dist: wheel (>=0.31.0) ; extra == 'test'
Requires-Dist: setuptools (>=38.6.0) ; extra == 'test'
Requires-Dist: twine (>=1.11.0) ; extra == 'test'
Requires-Dist: flake8 ; extra == 'test'
Requires-Dist: tox ; extra == 'test'
Requires-Dist: mock ; extra == 'test'
Requires-Dist: ipython ; extra == 'test'
Requires-Dist: papermill[dev] ; extra == 'test'
Requires-Dist: pytest (>=4.1) ; extra == 'test'
Requires-Dist: pytest-cov (>=2.6.1) ; extra == 'test'
Requires-Dist: pytest-mock (>=1.10) ; extra == 'test'
Requires-Dist: pytest-env (>=0.6.2) ; extra == 'test'
Requires-Dist: codecov ; extra == 'test'
Requires-Dist: coverage ; extra == 'test'
